{
  "project_info": {
    "project_number": "923898701140",
    "project_id": "login-7aa6a",
    "storage_bucket": "login-7aa6a.firebasestorage.app"
  },
  "client": [
    {
      "client_info": {
        "mobilesdk_app_id": "1:923898701140:android:35ffa6f5dfd7040b14d4c1",
        "android_client_info": {
          "package_name": "com.example.login_page"
        }
      },
      "oauth_client": [],
      "api_key": [
        {
          "current_key": "AIzaSyBeBHSGnYvyyzrmY8iIvCn4uPXQEJvao2U"
        }
      ],
      "services": {
        "appinvite_service": {
          "other_platform_oauth_client": []
        }
      }
    }
  ],
  "configuration_version": "1"
}